{
  "cuisines": [
    "American",
    "Chinese",
    "Coffee/Tea",
    "Pizza",
    "Mexican",
    "Japanese",
    "Latin American",
    "Italian",
    "Bakery Products/Desserts",
    "Caribbean",
    "Chicken",
    "Other",
    "Donuts",
    "Spanish",
    "Juice, Smoothies, Fruit Salads",
    "Asian/Asian Fusion",
    "Hamburgers",
    "Sandwiches",
    "Korean",
    "Frozen Desserts",
    "Thai",
    "Jewish/Kosher",
    "Indian",
    "Tex-Mex",
    "Mediterranean",
    "French",
    "Middle Eastern",
    "Seafood",
    "Bagels/Pretzels",
    "Irish",
    "Sandwiches/Salads/Mixed Buffet",
    "New American",
    "Bottled Beverages",
    "Greek",
    "Salads",
    "Eastern European",
    "Southeast Asian",
    "Peruvian",
    "Steakhouse",
    "African",
    "Fusion",
    "Bangladeshi",
    "Vegan",
    "Turkish",
    "Soul Food",
    "Vegetarian",
    "Barbecue",
    "Soups/Salads/Sandwiches",
    "Hawaiian",
    "Tapas",
    "Continental",
    "Russian",
    "Pakistani",
    "Pancakes/Waffles",
    "Filipino",
    "Chinese/Japanese",
    "Brazilian",
    "Hotdogs",
    "German",
    "Hotdogs/Pretzels",
    "Australian",
    "Creole",
    "Ethiopian",
    "Californian",
    "Chinese/Cuban",
    "Polish",
    "New French",
    "English",
    "Afghan",
    "Egyptian",
    "Indonesian",
    "Portuguese",
    "Moroccan",
    "Armenian",
    "Fruits/Vegetables",
    "Scandinavian",
    "Cajun",
    "Nuts/Confectionary",
    "Lebanese",
    "Creole/Cajun",
    "Iranian",
    "Soups",
    "Southwestern",
    "Basque",
    "Czech",
    "Chilean",
    "Chimichurri",
    "Haute Cuisine",
    "Polynesian"
  ],
  "dietary": ["Vegetarian", "Vegan", "Kosher"],
  "foodTypes": [
    "Bar",
    "Cafe",
    "Coffee Shop",
    "Bakery",
    "Fast Food",
    "Breakfast",
    "Pizza",
    "Sandwich Shop",
    "Dessert",
    "Catering",
    "Bagel Shop",
    "Brunch",
    "Sushi",
    "Seafood",
    "Donut Shop",
    "Ice Cream",
    "Night Club",
    "Juice Bar",
    "Wine Bar",
    "Tea House",
    "Bar & Grill",
    "Deli",
    "Diner",
    "Pub",
    "Steakhouse",
    "Fine Dining",
    "Ramen",
    "Internet Cafe",
    "BBQ",
    "Buffet",
    "Acai Shop",
    "Food Court",
    "Candy Store",
    "Chocolate Shop",
    "Dog Cafe",
    "Cat Cafe"
  ],
  "minimumSanitationGrades": ["N", "A", "Z", "B", "C", "P"],
  "priceRanges": ["$", "$$", "$$$", "$$$$"]
}
